zendesk/__init__.py
zendesk/_hooks/__init__.py
zendesk/_hooks/registration.py
zendesk/_hooks/sdkhooks.py
zendesk/_hooks/types.py
zendesk/_version.py
zendesk/account_settings.py
zendesk/activity_stream.py
zendesk/approval_requests.py
zendesk/approval_workflow_instances.py
zendesk/assigneefieldassignableagents.py
zendesk/assigneefieldassignablegroups.py
zendesk/attachments.py
zendesk/audit_logs.py
zendesk/automations.py
zendesk/basesdk.py
zendesk/basics.py
zendesk/bookmarks.py
zendesk/brand_agents.py
zendesk/brands.py
zendesk/channel_framework.py
zendesk/conversation_log.py
zendesk/custom_object_fields.py
zendesk/custom_object_records.py
zendesk/custom_objects.py
zendesk/custom_roles.py
zendesk/custom_ticket_statuses.py
zendesk/deletion_schedules.py
zendesk/dynamic_content.py
zendesk/dynamic_content_item_variants.py
zendesk/email_notifications.py
zendesk/errors/__init__.py
zendesk/errors/apierror.py
zendesk/errors/batchjobresponse_error.py
zendesk/errors/error.py
zendesk/errors/errorresponse.py
zendesk/errors/errors.py
zendesk/errors/no_response_error.py
zendesk/errors/recoversuspendedticketunprocessablecontentresponse_error.py
zendesk/errors/responsevalidationerror.py
zendesk/errors/skillbasedroutingattributevalueserror.py
zendesk/errors/zendeskerror.py
zendesk/essentials_card.py
zendesk/global_clients.py
zendesk/grant_type_tokens.py
zendesk/group_memberships.py
zendesk/group_sla_policies.py
zendesk/groups.py
zendesk/httpclient.py
zendesk/incremental_export.py
zendesk/incremental_skill_based_routing_sdk.py
zendesk/job_statuses.py
zendesk/locales.py
zendesk/lookup_relationships.py
zendesk/macros.py
zendesk/models/__init__.py
zendesk/models/accountsettingsactivefeaturesobject.py
zendesk/models/accountsettingsagentobject.py
zendesk/models/accountsettingsapiobject.py
zendesk/models/accountsettingsappsobject.py
zendesk/models/accountsettingsbillingobject.py
zendesk/models/accountsettingsbrandingobject.py
zendesk/models/accountsettingsbrandsobject.py
python_zendesk-0.1.17.dist-info/METADATA
python_zendesk-0.1.17.dist-info/WHEEL
python_zendesk-0.1.17.dist-info/RECORD
