Metadata-Version: 2.3
Name: python-zendesk
Version: 0.1.17
Summary: Python Client SDK for Zendesk Support API.
Author: Ben Meyer-Meisel
Requires-Python: >=3.9.2
Classifier: Programming Language :: Python :: 3
Classifier: Programming Language :: Python :: 3.10
Classifier: Programming Language :: Python :: 3.11
Classifier: Programming Language :: Python :: 3.12
Classifier: Programming Language :: Python :: 3.13
Requires-Dist: httpcore (>=1.0.9)
Requires-Dist: httpx (>=0.28.1)
Requires-Dist: jsonpath-python (>=1.0.6)
Requires-Dist: pydantic (>=2.11.2)
Requires-Dist: pyyaml (>=6.0.2,<7.0.0)
